fsm-assignments/problem2_traffic/traffic_light.v
module traffic_light(
    input  wire clk,
    input  wire rst,
    input  wire tick,
    output wire ns_g,
    output wire ns_y,
    output wire ns_r,
    output wire ew_g,
    output wire ew_y,
    output wire ew_r
);

    // State encoding
    parameter NS_GREEN  = 2'd0,
              NS_YELLOW = 2'd1,
              EW_GREEN  = 2'd2,
              EW_YELLOW = 2'd3;

    reg [1:0] state_present, state_next;

    // Phase durations
    parameter D_NS_GREEN  = 5,
              D_NS_YELLOW = 2,
              D_EW_GREEN  = 5,
              D_EW_YELLOW = 2;

    reg [2:0] phase_cnt_present, phase_cnt_next;

    // Next-state logic
    always @(*) begin
        state_next      = state_present;
        phase_cnt_next  = phase_cnt_present;

        if (tick) begin
            case (state_present)
                NS_GREEN: begin
                    if (phase_cnt_present == D_NS_GREEN-1) begin
                        state_next     = NS_YELLOW;
                        phase_cnt_next = 0;
                    end else begin
                        phase_cnt_next = phase_cnt_present + 1;
                    end
                end

                NS_YELLOW: begin
                    if (phase_cnt_present == D_NS_YELLOW-1) begin
                        state_next     = EW_GREEN;
                        phase_cnt_next = 0;
                    end else begin
                        phase_cnt_next = phase_cnt_present + 1;
                    end
                end

                EW_GREEN: begin
                    if (phase_cnt_present == D_EW_GREEN-1) begin
                        state_next     = EW_YELLOW;
                        phase_cnt_next = 0;
                    end else begin
                        phase_cnt_next = phase_cnt_present + 1;
                    end
                end

                EW_YELLOW: begin
                    if (phase_cnt_present == D_EW_YELLOW-1) begin
                        state_next     = NS_GREEN;
                        phase_cnt_next = 0;
                    end else begin
                        phase_cnt_next = phase_cnt_present + 1;
                    end
                end
            endcase
        end
    end

    // State registers
    always @(posedge clk) begin
        if (rst) begin
            state_present     <= NS_GREEN;
            phase_cnt_present <= 0;
        end else begin
            state_present     <= state_next;
            phase_cnt_present <= phase_cnt_next;
        end
    end

    // Outputs
    assign ns_g = (state_present == NS_GREEN);
    assign ns_y = (state_present == NS_YELLOW);
    assign ns_r = ~(ns_g | ns_y);

    assign ew_g = (state_present == EW_GREEN);
    assign ew_y = (state_present == EW_YELLOW);
    assign ew_r = ~(ew_g | ew_y);

endmodule

fsm-assignments/problem2_traffic/tb_traffic_light.v
`timescale 1ns/1ps

module tb_traffic_light;
  reg clk;
  reg rst;
  reg tick;
  wire ns_g, ns_y, ns_r, ew_g, ew_y, ew_r;

  // DUT
  traffic_light dut(
    .clk(clk), .rst(rst), .tick(tick),
    .ns_g(ns_g), .ns_y(ns_y), .ns_r(ns_r),
    .ew_g(ew_g), .ew_y(ew_y), .ew_r(ew_r)
  );

  // Clock: 20 ns period = 50 MHz
  initial clk = 0;
  always #10 clk = ~clk;

  // Fast tick for simulation: pulse every 20 clk cycles
  integer cyc;
  initial begin
    cyc = 0;
    tick = 0;
  end
  always @(posedge clk) begin
    cyc <= cyc + 1;
    if (cyc % 20 == 0) tick <= 1;
    else tick <= 0;
  end

  // Stimulus
  initial begin
    $dumpfile("dump.vcd");
    $dumpvars(0, tb_traffic_light);

    rst = 1; #40;  // hold reset for 2 clock cycles
    rst = 0;

    #4000;        // run simulation
    $finish;
  end

  // Display state at every tick
  always @(posedge clk) begin
    if (tick) begin
      $display("time=%0t ns_g=%0b ns_y=%0b ns_r=%0b ew_g=%0b ew_y=%0b ew_r=%0b",
               $time, ns_g, ns_y, ns_r, ew_g, ew_y, ew_r);
    end
  end

endmodule

fsm-assignments/problem2_traffic/waves/dump.vcd
$date
	Mon Aug 18 19:52:37 2025
$end
$version
	Icarus Verilog
$end
$timescale
	1ps
$end
$scope module tb_traffic_light $end
$var wire 1 ! ns_y $end
$var wire 1 " ns_r $end
$var wire 1 # ns_g $end
$var wire 1 $ ew_y $end
$var wire 1 % ew_r $end
$var wire 1 & ew_g $end
$var reg 1 ' clk $end
$var reg 1 ( rst $end
$var reg 1 ) tick $end
$var integer 32 * cyc [31:0] $end
$scope module dut $end
$var wire 1 ' clk $end
$var wire 1 % ew_r $end
$var wire 1 " ns_r $end
$var wire 1 ( rst $end
$var wire 1 ) tick $end
$var wire 1 ! ns_y $end
$var wire 1 # ns_g $end
$var wire 1 $ ew_y $end
$var wire 1 & ew_g $end
$var reg 3 + phase_cnt_next [2:0] $end
$var reg 3 , phase_cnt_present [2:0] $end
$var reg 2 - state_next [1:0] $end
$var reg 2 . state_present [1:0] $end
$upscope $end
$upscope $end
$enddefinitions $end
#0
$dumpvars
bx .
bx -
bx ,
bx +
b0 *
0)
1(
0'
x&
x%
x$
x#
x"
x!
$end
#10000
0"
1%
b1 +
b0 -
b0 ,
1#
0!
0&
0$
b0 .
1)
b1 *
1'
#20000
0'
#30000
b0 +
0)
b10 *
1'
#40000
0'
0(
#50000
b11 *
1'
#60000
0'
#70000
b100 *
1'
#80000
0'
#90000
b101 *
1'
#100000
0'
#110000
b110 *
1'
#120000
0'
#130000
b111 *
1'
#140000
0'
#150000
b1000 *
1'
#160000
0'
#170000
b1001 *
1'
#180000
0'
#190000
b1010 *
1'
#200000
0'
#210000
b1011 *
1'
#220000
0'
#230000
b1100 *
1'
#240000
0'
#250000
b1101 *
1'
#260000
0'
#270000
b1110 *
1'
#280000
0'
#290000
b1111 *
1'
#300000
0'
#310000
b10000 *
1'
#320000
0'
#330000
b10001 *
1'
#340000
0'
#350000
b10010 *
1'
#360000
0'
#370000
b10011 *
1'
#380000
0'
#390000
b10100 *
1'
#400000
0'
#410000
b1 +
1)
b10101 *
1'
#420000
0'
#430000
0)
b10110 *
b1 ,
1'
#440000
0'
#450000
b10111 *
1'
#460000
0'
#470000
b11000 *
1'
#480000
0'
#490000
b11001 *
1'
#500000
0'
#510000
b11010 *
1'
#520000
0'
#530000
b11011 *
1'
#540000
0'
#550000
b11100 *
1'
#560000
0'
#570000
b11101 *
1'
#580000
0'
#590000
b11110 *
1'
#600000
0'
#610000
b11111 *
1'
#620000
0'
#630000
b100000 *
1'
#640000
0'
#650000
b100001 *
1'
#660000
0'
#670000
b100010 *
1'
#680000
0'
#690000
b100011 *
1'
#700000
0'
#710000
b100100 *
1'
#720000
0'
#730000
b100101 *
1'
#740000
0'
#750000
b100110 *
1'
#760000
0'
#770000
b100111 *
1'
#780000
0'
#790000
b101000 *
1'
#800000
0'
#810000
b10 +
1)
b101001 *
1'
#820000
0'
#830000
0)
b101010 *
b10 ,
1'
#840000
0'
#850000
b101011 *
1'
#860000
0'
#870000
b101100 *
1'
#880000
0'
#890000
b101101 *
1'
#900000
0'
#910000
b101110 *
1'
#920000
0'
#930000
b101111 *
1'
#940000
0'
#950000
b110000 *
1'
#960000
0'
#970000
b110001 *
1'
#980000
0'
#990000
b110010 *
1'
#1000000
0'
#1010000
b110011 *
1'
#1020000
0'
#1030000
b110100 *
1'
#1040000
0'
#1050000
b110101 *
1'
#1060000
0'
#1070000
b110110 *
1'
#1080000
0'
#1090000
b110111 *
1'
#1100000
0'
#1110000
b111000 *
1'
#1120000
0'
#1130000
b111001 *
1'
#1140000
0'
#1150000
b111010 *
1'
#1160000
0'
#1170000
b111011 *
1'
#1180000
0'
#1190000
b111100 *
1'
#1200000
0'
#1210000
b11 +
1)
b111101 *
1'
#1220000
0'
#1230000
0)
b111110 *
b11 ,
1'
#1240000
0'
#1250000
b111111 *
1'
#1260000
0'
#1270000
b1000000 *
1'
#1280000
0'
#1290000
b1000001 *
1'
#1300000
0'
#1310000
b1000010 *
1'
#1320000
0'
#1330000
b1000011 *
1'
#1340000
0'
#1350000
b1000100 *
1'
#1360000
0'
#1370000
b1000101 *
1'
#1380000
0'
#1390000
b1000110 *
1'
#1400000
0'
#1410000
b1000111 *
1'
#1420000
0'
#1430000
b1001000 *
1'
#1440000
0'
#1450000
b1001001 *
1'
#1460000
0'
#1470000
b1001010 *
1'
#1480000
0'
#1490000
b1001011 *
1'
#1500000
0'
#1510000
b1001100 *
1'
#1520000
0'
#1530000
b1001101 *
1'
#1540000
0'
#1550000
b1001110 *
1'
#1560000
0'
#1570000
b1001111 *
1'
#1580000
0'
#1590000
b1010000 *
1'
#1600000
0'
#1610000
b100 +
1)
b1010001 *
1'
#1620000
0'
#1630000
0)
b1010010 *
b100 ,
1'
#1640000
0'
#1650000
b1010011 *
1'
#1660000
0'
#1670000
b1010100 *
1'
#1680000
0'
#1690000
b1010101 *
1'
#1700000
0'
#1710000
b1010110 *
1'
#1720000
0'
#1730000
b1010111 *
1'
#1740000
0'
#1750000
b1011000 *
1'
#1760000
0'
#1770000
b1011001 *
1'
#1780000
0'
#1790000
b1011010 *
1'
#1800000
0'
#1810000
b1011011 *
1'
#1820000
0'
#1830000
b1011100 *
1'
#1840000
0'
#1850000
b1011101 *
1'
#1860000
0'
#1870000
b1011110 *
1'
#1880000
0'
#1890000
b1011111 *
1'
#1900000
0'
#1910000
b1100000 *
1'
#1920000
0'
#1930000
b1100001 *
1'
#1940000
0'
#1950000
b1100010 *
1'
#1960000
0'
#1970000
b1100011 *
1'
#1980000
0'
#1990000
b1100100 *
1'
#2000000
0'
#2010000
b0 +
b1 -
1)
b1100101 *
1'
#2020000
0'
#2030000
0)
b1100110 *
b0 ,
0#
1!
b1 .
1'
#2040000
0'
#2050000
b1100111 *
1'
#2060000
0'
#2070000
b1101000 *
1'
#2080000
0'
#2090000
b1101001 *
1'
#2100000
0'
#2110000
b1101010 *
1'
#2120000
0'
#2130000
b1101011 *
1'
#2140000
0'
#2150000
b1101100 *
1'
#2160000
0'
#2170000
b1101101 *
1'
#2180000
0'
#2190000
b1101110 *
1'
#2200000
0'
#2210000
b1101111 *
1'
#2220000
0'
#2230000
b1110000 *
1'
#2240000
0'
#2250000
b1110001 *
1'
#2260000
0'
#2270000
b1110010 *
1'
#2280000
0'
#2290000
b1110011 *
1'
#2300000
0'
#2310000
b1110100 *
1'
#2320000
0'
#2330000
b1110101 *
1'
#2340000
0'
#2350000
b1110110 *
1'
#2360000
0'
#2370000
b1110111 *
1'
#2380000
0'
#2390000
b1111000 *
1'
#2400000
0'
#2410000
b1 +
1)
b1111001 *
1'
#2420000
0'
#2430000
0)
b1111010 *
b1 ,
1'
#2440000
0'
#2450000
b1111011 *
1'
#2460000
0'
#2470000
b1111100 *
1'
#2480000
0'
#2490000
b1111101 *
1'
#2500000
0'
#2510000
b1111110 *
1'
#2520000
0'
#2530000
b1111111 *
1'
#2540000
0'
#2550000
b10000000 *
1'
#2560000
0'
#2570000
b10000001 *
1'
#2580000
0'
#2590000
b10000010 *
1'
#2600000
0'
#2610000
b10000011 *
1'
#2620000
0'
#2630000
b10000100 *
1'
#2640000
0'
#2650000
b10000101 *
1'
#2660000
0'
#2670000
b10000110 *
1'
#2680000
0'
#2690000
b10000111 *
1'
#2700000
0'
#2710000
b10001000 *
1'
#2720000
0'
#2730000
b10001001 *
1'
#2740000
0'
#2750000
b10001010 *
1'
#2760000
0'
#2770000
b10001011 *
1'
#2780000
0'
#2790000
b10001100 *
1'
#2800000
0'
#2810000
b0 +
b10 -
1)
b10001101 *
1'
#2820000
0'
#2830000
1"
0%
0)
b10001110 *
b0 ,
0!
1&
b10 .
1'
#2840000
0'
#2850000
b10001111 *
1'
#2860000
0'
#2870000
b10010000 *
1'
#2880000
0'
#2890000
b10010001 *
1'
#2900000
0'
#2910000
b10010010 *
1'
#2920000
0'
#2930000
b10010011 *
1'
#2940000
0'
#2950000
b10010100 *
1'
#2960000
0'
#2970000
b10010101 *
1'
#2980000
0'
#2990000
b10010110 *
1'
#3000000
0'
#3010000
b10010111 *
1'
#3020000
0'
#3030000
b10011000 *
1'
#3040000
0'
#3050000
b10011001 *
1'
#3060000
0'
#3070000
b10011010 *
1'
#3080000
0'
#3090000
b10011011 *
1'
#3100000
0'
#3110000
b10011100 *
1'
#3120000
0'
#3130000
b10011101 *
1'
#3140000
0'
#3150000
b10011110 *
1'
#3160000
0'
#3170000
b10011111 *
1'
#3180000
0'
#3190000
b10100000 *
1'
#3200000
0'
#3210000
b1 +
1)
b10100001 *
1'
#3220000
0'
#3230000
0)
b10100010 *
b1 ,
1'
#3240000
0'
#3250000
b10100011 *
1'
#3260000
0'
#3270000
b10100100 *
1'
#3280000
0'
#3290000
b10100101 *
1'
#3300000
0'
#3310000
b10100110 *
1'
#3320000
0'
#3330000
b10100111 *
1'
#3340000
0'
#3350000
b10101000 *
1'
#3360000
0'
#3370000
b10101001 *
1'
#3380000
0'
#3390000
b10101010 *
1'
#3400000
0'
#3410000
b10101011 *
1'
#3420000
0'
#3430000
b10101100 *
1'
#3440000
0'
#3450000
b10101101 *
1'
#3460000
0'
#3470000
b10101110 *
1'
#3480000
0'
#3490000
b10101111 *
1'
#3500000
0'
#3510000
b10110000 *
1'
#3520000
0'
#3530000
b10110001 *
1'
#3540000
0'
#3550000
b10110010 *
1'
#3560000
0'
#3570000
b10110011 *
1'
#3580000
0'
#3590000
b10110100 *
1'
#3600000
0'
#3610000
b10 +
1)
b10110101 *
1'
#3620000
0'
#3630000
0)
b10110110 *
b10 ,
1'
#3640000
0'
#3650000
b10110111 *
1'
#3660000
0'
#3670000
b10111000 *
1'
#3680000
0'
#3690000
b10111001 *
1'
#3700000
0'
#3710000
b10111010 *
1'
#3720000
0'
#3730000
b10111011 *
1'
#3740000
0'
#3750000
b10111100 *
1'
#3760000
0'
#3770000
b10111101 *
1'
#3780000
0'
#3790000
b10111110 *
1'
#3800000
0'
#3810000
b10111111 *
1'
#3820000
0'
#3830000
b11000000 *
1'
#3840000
0'
#3850000
b11000001 *
1'
#3860000
0'
#3870000
b11000010 *
1'
#3880000
0'
#3890000
b11000011 *
1'
#3900000
0'
#3910000
b11000100 *
1'
#3920000
0'
#3930000
b11000101 *
1'
#3940000
0'
#3950000
b11000110 *
1'
#3960000
0'
#3970000
b11000111 *
1'
#3980000
0'
#3990000
b11001000 *
1'
#4000000
0'
#4010000
b11 +
1)
b11001001 *
1'
#4020000
0'
#4030000
0)
b11001010 *
b11 ,
1'
