fsm-assignments/problem1_seqdet/seq_detect_mealy.v
module seq_detect_mealy(
    input wire clk,
    input wire rst,        // sync active-high
    input wire din,        // serial input bit per clock
    output reg y           // 1-cycle pulse when pattern ...1101 seen
);

    // Abstract state encoding
    
        parameter init   = 2'b00, // No match
         one   = 2'b01, // Seen '1'
         two  = 2'b10, // Seen '11'
         three = 2'b11;  // Seen '110'
    

    reg [1:0] state_present, state_next;

    // State register
    always @(posedge clk) begin
        if (rst)
            state_present <= init;
        else
            state_present <= state_next;
        
        y<=0;
        if(state_present==three && din==1)begin
            y<=1;
        end
    end

    // Next state & output logic
    always @(*) begin
        state_next = state_present; // default stay

        case (state_present)
            init: begin
                if (din)
                    state_next = one;
                else
                    state_next = init;
            end

            one: begin
                if (din)
                    state_next = two;
                else
                    state_next = init;
            end

            two: begin
                if (din)
                    state_next = two;
                else
                    state_next = three;
            end

            three: begin
                if (din) begin
                   
                    state_next = one; // Overlap handling
                end else
                    state_next = init;
            end

            default: state_next = init;
        endcase
    end

endmodule

fsm-assignments/problem1_seqdet/tb_seq_detect_mealy.v
`timescale 1ns/1ps

module tb_seq_detect_mealy;
    reg clk, rst, din;
    wire y;

    // DUT instantiation
    seq_detect_mealy dut (
        .clk(clk),
        .rst(rst),
        .din(din),
        .y(y)
    );

    // 1) Clock generation: 100 MHz -> 10 ns period
    initial begin
        clk = 0;
        forever #5 clk = ~clk; // toggle every 5ns
    end

    // 2) Drive a bitstream with overlaps: 11011011101
    reg [10:0] bitstream = 11'b11011011101;
    integer i;

    initial begin
        // Dump file for GTKWave
        $dumpfile("dump.vcd");
        $dumpvars(0, tb_seq_detect_mealy);

        // Initialize
        rst = 1;
        din = 0;#5;

        // Apply reset for a couple of cycles
        #15 rst = 0;

        // Send bits MSB -> LSB
        for (i = 10; i >= 0; i = i - 1) begin
            din = bitstream[i];
            #10; // one clock period
        end

        #20 $finish;
    end

    // 3) Log time, din, y
    initial begin
        $display("Time\tclk\trst\tdin\ty");
        $monitor("%0dns\t%b\t%b\t%b\t%b", $time, clk, rst, din, y);
    end

endmodule

fsm-assignments/problem1_seqdet/waves/dump.vcd
$date
	Mon Aug 18 19:38:20 2025
$end
$version
	Icarus Verilog
$end
$timescale
	1ps
$end
$scope module tb_seq_detect_mealy $end
$var wire 1 ! y $end
$var reg 11 " bitstream [10:0] $end
$var reg 1 # clk $end
$var reg 1 $ din $end
$var reg 1 % rst $end
$var integer 32 & i [31:0] $end
$scope module dut $end
$var wire 1 # clk $end
$var wire 1 $ din $end
$var wire 1 % rst $end
$var reg 2 ' state_next [1:0] $end
$var reg 2 ( state_present [1:0] $end
$var reg 1 ! y $end
$upscope $end
$upscope $end
$enddefinitions $end
#0
$dumpvars
bx (
b0 '
bx &
1%
0$
0#
b11011011101 "
x!
$end
#5000
0!
b0 (
1#
#10000
0#
#15000
1#
#20000
b1 '
0#
1$
b1010 &
0%
#25000
b10 '
b1 (
1#
#30000
0#
b1001 &
#35000
b10 (
1#
#40000
b11 '
0#
0$
b1000 &
#45000
b0 '
b11 (
1#
#50000
b1 '
0#
1$
b111 &
#55000
b10 '
1!
b1 (
1#
#60000
0#
b110 &
#65000
0!
b10 (
1#
#70000
b11 '
0#
0$
b101 &
#75000
b0 '
b11 (
1#
#80000
b1 '
0#
1$
b100 &
#85000
b10 '
1!
b1 (
1#
#90000
0#
b11 &
#95000
0!
b10 (
1#
#100000
0#
b10 &
#105000
1#
#110000
b11 '
0#
0$
b1 &
#115000
b0 '
b11 (
1#
#120000
b1 '
0#
1$
b0 &
#125000
b10 '
1!
b1 (
1#
#130000
0#
b11111111111111111111111111111111 &
#135000
0!
b10 (
1#
