fsm-assignments/problem3_vending/vending_mealy.v
module vending_mealy(
    input  wire clk,
    input  wire rst,      // sync active-high
    input  wire [1:0] coin, // 01=5, 10=10, 00=idle
    output reg  dispense, // 1-cycle pulse
    output reg  chg5      // 1-cycle pulse
);

    // State encoding
    parameter idle=2'b00, five=2'b01, ten=2'b10, fifteen=2'b11;

    reg [1:0] state_present, state_next;

    // State register
    always @(posedge clk) begin
        if (rst)
            state_present <= idle;
        else
            state_present <= state_next;

        dispense <= 0; // Reset dispense signal
        chg5 <= 0;     // Reset change signal
        if(state_present==ten && coin==2'b10)begin
            dispense <= 1; // Dispense on 10+10
        end else if(state_present==fifteen && coin==2'b01) begin
            dispense <= 1; // Dispense on 15+5
        end else if(state_present==fifteen && coin==2'b10) begin
            dispense <= 1; // Dispense on 15+10
            chg5 <= 1;     // Change for 5
        end
    end

    // Next-state + Mealy outputs
    always @(*) begin
        // defaults
        state_next = state_present;
     

        case (state_present)
            idle: begin
                if (coin == 2'b01) state_next = five;
                else if (coin == 2'b10) state_next = ten;
            end

            five: begin
                if (coin == 2'b01) state_next = ten;
                else if (coin == 2'b10) state_next = fifteen;
            end

            ten: begin
                if (coin == 2'b01) state_next = fifteen;
                else if (coin == 2'b10) begin
                   
                    state_next = idle;
                end
            end

            fifteen: begin
                if (coin == 2'b01) begin
                    
                    state_next = idle;
                end
                else if (coin == 2'b10) begin
                   
                    state_next = idle;
                end
            end
        endcase
    end
endmodule

fsm-assignments/problem3_vending/tb_vending_mealy.v
`timescale 1ns/1ps

module tb_vending_mealy;
    reg clk, rst;
    reg [1:0] coin;   // 01=5, 10=10, 00=idle
    wire dispense, chg5;

    // DUT instantiation
    vending_mealy dut (
        .clk(clk),
        .rst(rst),
        .coin(coin),
        .dispense(dispense),
        .chg5(chg5)
    );

    // Clock generation: 100MHz -> 10ns period
    initial begin
        clk = 0;
        forever #5 clk = ~clk;
    end

    // Task to insert a coin (with idle cycle after)
    task insert_coin(input [1:0] c);
    begin
        coin = c; #10;
        coin = 2'b00; #10;
    end
    endtask

    // Stimulus
    initial begin
        $dumpfile("tb_vending_mealy.vcd");
        $dumpvars(0, tb_vending_mealy);

        // Reset
        rst = 1; coin = 2'b00;
        #12 rst = 0;

        // --------------------------
        // Exact 20 scenarios
        // --------------------------
        $display("Test: 5 + 5 + 10 = 20 (dispense)");
        insert_coin(2'b01); // 5
        insert_coin(2'b01); // 5
        insert_coin(2'b10); // 10
        #20;

        $display("Test: 5 + 10 + 5 = 20 (dispense)");
        insert_coin(2'b01);
        insert_coin(2'b10);
        insert_coin(2'b01);
        #20;

        $display("Test: 10 + 5 + 5 = 20 (dispense)");
        insert_coin(2'b10);
        insert_coin(2'b01);
        insert_coin(2'b01);
        #20;

        $display("Test: 10 + 10 = 20 (dispense)");
        insert_coin(2'b10);
        insert_coin(2'b10);
        #20;

        $display("Test: 15 + 5 = 20 (dispense)");
        insert_coin(2'b10);
        insert_coin(2'b01);
        insert_coin(2'b01);
        insert_coin(2'b01);
        #20;

        // --------------------------
        // Overpay = 25
        // --------------------------
        $display("Test: 15 + 10 = 25 (dispense + chg5)");
        insert_coin(2'b10);
        insert_coin(2'b01);
        insert_coin(2'b01);
        insert_coin(2'b10);
        #20;

        // --------------------------
        // Underpayment (no vend)
        // --------------------------
        $display("Test: just 5 (no vend)");
        insert_coin(2'b01);
        #20;

        $display("Test: just 10 (no vend)");
        insert_coin(2'b10);
        #20;

        $display("Test: 10 + 10 = 20 (vend)");
        insert_coin(2'b10);
        #20;

        $display("Test: 10+5 + 10 = 25 (vend with change)");
        insert_coin(2'b10); // 10
        insert_coin(2'b01); // 5
        insert_coin(2'b10); // 10
        #20;
    

        // --------------------------
        // Reset behavior
        // --------------------------
        $display("Test: reset during transaction");
        insert_coin(2'b10);
        insert_coin(2'b01); // now total=15
        rst = 1; #10; rst = 0; // reset in middle
        insert_coin(2'b10); // should behave as fresh
        #20;

        $finish;
    end

endmodule

fsm-assignments/problem3_vending/waves/tb_vending_mealy.vcd
$date
	Mon Aug 18 19:43:09 2025
$end
$version
	Icarus Verilog
$end
$timescale
	1ps
$end
$scope module tb_vending_mealy $end
$var wire 1 ! dispense $end
$var wire 1 " chg5 $end
$var reg 1 # clk $end
$var reg 2 $ coin [1:0] $end
$var reg 1 % rst $end
$scope module dut $end
$var wire 1 # clk $end
$var wire 2 & coin [1:0] $end
$var wire 1 % rst $end
$var reg 1 " chg5 $end
$var reg 1 ! dispense $end
$var reg 2 ' state_next [1:0] $end
$var reg 2 ( state_present [1:0] $end
$upscope $end
$scope task insert_coin $end
$var reg 2 ) c [1:0] $end
$upscope $end
$upscope $end
$enddefinitions $end
#0
$dumpvars
bx )
bx (
bx '
b0 &
1%
b0 $
0#
x"
x!
$end
#5000
b0 '
0"
0!
b0 (
1#
#10000
0#
#12000
b1 '
b1 $
b1 &
b1 )
0%
#15000
b10 '
b1 (
1#
#20000
0#
#22000
b1 '
b0 $
b0 &
#25000
1#
#30000
0#
#32000
b10 '
b1 $
b1 &
#35000
b11 '
b10 (
1#
#40000
0#
#42000
b10 '
b0 $
b0 &
#45000
1#
#50000
0#
#52000
b0 '
b10 $
b10 &
b10 )
#55000
b10 '
1!
b0 (
1#
#60000
0#
#62000
b0 '
b0 $
b0 &
#65000
0!
1#
#70000
0#
#75000
1#
#80000
0#
#85000
1#
#90000
0#
#92000
b1 '
b1 $
b1 &
b1 )
#95000
b10 '
b1 (
1#
#100000
0#
#102000
b1 '
b0 $
b0 &
#105000
1#
#110000
0#
#112000
b11 '
b10 $
b10 &
b10 )
#115000
b0 '
b11 (
1#
#120000
0#
#122000
b11 '
b0 $
b0 &
#125000
1#
#130000
0#
#132000
b0 '
b1 $
b1 &
b1 )
#135000
b1 '
1!
b0 (
1#
#140000
0#
#142000
b0 '
b0 $
b0 &
#145000
0!
1#
#150000
0#
#155000
1#
#160000
0#
#165000
1#
#170000
0#
#172000
b10 '
b10 $
b10 &
b10 )
#175000
b0 '
b10 (
1#
#180000
0#
#182000
b10 '
b0 $
b0 &
#185000
1#
#190000
0#
#192000
b11 '
b1 $
b1 &
b1 )
#195000
b0 '
b11 (
1#
#200000
0#
#202000
b11 '
b0 $
b0 &
#205000
1#
#210000
0#
#212000
b0 '
b1 $
b1 &
#215000
b1 '
1!
b0 (
1#
#220000
0#
#222000
b0 '
b0 $
b0 &
#225000
0!
1#
#230000
0#
#235000
1#
#240000
0#
#245000
1#
#250000
0#
#252000
b10 '
b10 $
b10 &
b10 )
#255000
b0 '
b10 (
1#
#260000
0#
#262000
b10 '
b0 $
b0 &
#265000
1#
#270000
0#
#272000
b0 '
b10 $
b10 &
#275000
b10 '
1!
b0 (
1#
#280000
0#
#282000
b0 '
b0 $
b0 &
#285000
0!
1#
#290000
0#
#295000
1#
#300000
0#
#305000
1#
#310000
0#
#312000
b10 '
b10 $
b10 &
#315000
b0 '
b10 (
1#
#320000
0#
#322000
b10 '
b0 $
b0 &
#325000
1#
#330000
0#
#332000
b11 '
b1 $
b1 &
b1 )
#335000
b0 '
b11 (
1#
#340000
0#
#342000
b11 '
b0 $
b0 &
#345000
1#
#350000
0#
#352000
b0 '
b1 $
b1 &
#355000
b1 '
1!
b0 (
1#
#360000
0#
#362000
b0 '
b0 $
b0 &
#365000
0!
1#
#370000
0#
#372000
b1 '
b1 $
b1 &
#375000
b10 '
b1 (
1#
#380000
0#
#382000
b1 '
b0 $
b0 &
#385000
1#
#390000
0#
#395000
1#
#400000
0#
#405000
1#
#410000
0#
#412000
b11 '
b10 $
b10 &
b10 )
#415000
b0 '
b11 (
1#
#420000
0#
#422000
b11 '
b0 $
b0 &
#425000
1#
#430000
0#
#432000
b0 '
b1 $
b1 &
b1 )
#435000
b1 '
1!
b0 (
1#
#440000
0#
#442000
b0 '
b0 $
b0 &
#445000
0!
1#
#450000
0#
#452000
b1 '
b1 $
b1 &
#455000
b10 '
b1 (
1#
#460000
0#
#462000
b1 '
b0 $
b0 &
#465000
1#
#470000
0#
#472000
b11 '
b10 $
b10 &
b10 )
#475000
b0 '
b11 (
1#
#480000
0#
#482000
b11 '
b0 $
b0 &
#485000
1#
#490000
0#
#495000
1#
#500000
0#
#505000
1#
#510000
0#
#512000
b0 '
b1 $
b1 &
b1 )
#515000
b1 '
1!
b0 (
1#
#520000
0#
#522000
b0 '
b0 $
b0 &
#525000
0!
1#
#530000
0#
#535000
1#
#540000
0#
#545000
1#
#550000
0#
#552000
b10 '
b10 $
b10 &
b10 )
#555000
b0 '
b10 (
1#
#560000
0#
#562000
b10 '
b0 $
b0 &
#565000
1#
#570000
0#
#575000
1#
#580000
0#
#585000
1#
#590000
0#
#592000
b0 '
b10 $
b10 &
#595000
b10 '
1!
b0 (
1#
#600000
0#
#602000
b0 '
b0 $
b0 &
#605000
0!
1#
#610000
0#
#615000
1#
#620000
0#
#625000
1#
#630000
0#
#632000
b10 '
b10 $
b10 &
#635000
b0 '
b10 (
1#
#640000
0#
#642000
b10 '
b0 $
b0 &
#645000
1#
#650000
0#
#652000
b11 '
b1 $
b1 &
b1 )
#655000
b0 '
b11 (
1#
#660000
0#
#662000
b11 '
b0 $
b0 &
#665000
1#
#670000
0#
#672000
b0 '
b10 $
b10 &
b10 )
#675000
b10 '
1"
1!
b0 (
1#
#680000
0#
#682000
b0 '
b0 $
b0 &
#685000
0"
0!
1#
#690000
0#
#695000
1#
#700000
0#
#705000
1#
#710000
0#
#712000
b10 '
b10 $
b10 &
#715000
b0 '
b10 (
1#
#720000
0#
#722000
b10 '
b0 $
b0 &
#725000
1#
#730000
0#
#732000
b11 '
b1 $
b1 &
b1 )
#735000
b0 '
b11 (
1#
#740000
0#
#742000
b11 '
b0 $
b0 &
#745000
1#
#750000
0#
#752000
1%
#755000
b0 '
b0 (
1#
#760000
0#
#762000
b10 '
b10 $
b10 &
b10 )
0%
#765000
b0 '
b10 (
1#
#770000
0#
#772000
b10 '
b0 $
b0 &
