fsm-assignments/problem4_link/slave_fsm.v
module slave_fsm(
  input  wire clk,
  input  wire rst,
  input  wire req,
  input  wire [7:0] data_in,
  output reg  ack,
  output reg [7:0] last_byte
);

  reg prev_req;
  reg [1:0] ack_cnt;

  always @(posedge clk) begin
    if (rst) begin
      prev_req  <= 0;
      ack       <= 0;
      ack_cnt   <= 0;
      last_byte <= 0;
    end else begin
      prev_req <= req;

      // detect rising edge of req
      if (req && !prev_req) begin
        last_byte <= data_in;
        ack       <= 1;
        ack_cnt   <= 1;
      end
      else if (ack) begin
        if (ack_cnt < 2) ack_cnt <= ack_cnt + 1;
        if ((ack_cnt >= 2) && !req) begin
          ack     <= 0;
          ack_cnt <= 0;
        end
      end
    end
  end

endmodule

fsm-assignments/problem4_link/master_fsm.v
module master_fsm(
  input  wire clk,
  input  wire rst,
  input  wire ack,
  output reg  req,
  output reg [7:0] data,
  output reg  done
);

  parameter NUM_BYTES = 4;

  // Memory with 4 data bytes
  reg [7:0] mem [0:NUM_BYTES-1];
  initial begin
    mem[0] = 8'hA0;
    mem[1] = 8'hA1;
    mem[2] = 8'hA2;
    mem[3] = 8'hA3;
  end

  // State encoding (no typedef, only localparam)
  localparam IDLE        = 2'b00,
             WAIT_ACK    = 2'b01,
             WAIT_ACK_LOW= 2'b10,
             DONE_STATE  = 2'b11;

  reg [1:0] state_present, state_next;
  reg [1:0] idx_present, idx_next;

  // Sequential state update
  always @(posedge clk) begin
    if (rst) begin
      state_present <= IDLE;
      idx_present   <= 0;
      req     <= 0;
      data    <= 0;
      done    <= 0;
    end else begin
      state_present <= state_next;
      idx_present   <= idx_next;
    end
  end

  // Combinational next state logic
  always @(*) begin
    // defaults
    state_next = state_present;
    idx_next   = idx_present;
    req     = req;
    data    = data;
    done    = 0;

    case (state_present)

      IDLE: begin
        data    = mem[idx_present];
        req     = 1;
        state_next = WAIT_ACK;
      end

      WAIT_ACK: begin
        if (ack) begin
          req     = 0;
          state_next = WAIT_ACK_LOW;
        end
      end

      WAIT_ACK_LOW: begin
        if (!ack) begin
          if (idx_present == NUM_BYTES-1) begin
            done    = 1;
            state_next = DONE_STATE;
          end else begin
            idx_next   = idx_present + 1;
            data    = mem[idx_present+1];
            req     = 1;
            state_next = WAIT_ACK;
          end
        end
      end

      DONE_STATE: begin
        state_next = IDLE;
      end

    endcase
  end

endmodule

fsm-assignments/problem4_link/link_top.v
module link_top(
  input  wire clk,
  input  wire rst,
  output wire done
);

  wire req, ack;
  wire [7:0] data;
  wire [7:0] last_byte;

  master_fsm master_inst(
    .clk(clk), .rst(rst), .ack(ack),
    .req(req), .data(data), .done(done)
  );

  slave_fsm slave_inst(
    .clk(clk), .rst(rst), .req(req),
    .data_in(data), .ack(ack), .last_byte(last_byte)
  );

endmodule

fsm-assignments/problem4_link/tb_link_top.v
`timescale 1ns/1ps
module tb_link_top;

  reg clk, rst;
  wire done;

  link_top dut(.clk(clk), .rst(rst), .done(done));

  // Clock
  initial clk = 0;
  always #5 clk = ~clk;  // 100MHz

  // Test sequence
  initial begin
    $dumpfile("dump.vcd");
    $dumpvars(0, tb_link_top);

    rst = 1; #20; rst = 0;

    $display("time  clk  req   ack   ack_cnt    data     last_byte   done");
    $monitor("%0t   %b    %b    %b   %b         %02h     %02h        %b",
      $time, clk, dut.master_inst.req, dut.slave_inst.ack,dut.slave_inst.ack_cnt,
      dut.master_inst.data, dut.slave_inst.last_byte, done);

    wait(done==1);
    #10;
    $finish;
  end

endmodule

fsm-assignments/problem4_link/waves/dump.vcd
$date
	Mon Aug 18 19:58:37 2025
$end
$version
	Icarus Verilog
$end
$timescale
	1ps
$end
$scope module tb_link_top $end
$var wire 1 ! done $end
$var reg 1 " clk $end
$var reg 1 # rst $end
$scope module dut $end
$var wire 1 " clk $end
$var wire 1 # rst $end
$var wire 1 $ req $end
$var wire 8 % last_byte [7:0] $end
$var wire 1 ! done $end
$var wire 8 & data [7:0] $end
$var wire 1 ' ack $end
$scope module master_inst $end
$var wire 1 " clk $end
$var wire 1 # rst $end
$var wire 1 ' ack $end
$var reg 8 ( data [7:0] $end
$var reg 1 ! done $end
$var reg 2 ) idx_next [1:0] $end
$var reg 2 * idx_present [1:0] $end
$var reg 1 $ req $end
$var reg 2 + state_next [1:0] $end
$var reg 2 , state_present [1:0] $end
$upscope $end
$scope module slave_inst $end
$var wire 1 " clk $end
$var wire 8 - data_in [7:0] $end
$var wire 1 $ req $end
$var wire 1 # rst $end
$var reg 1 ' ack $end
$var reg 2 . ack_cnt [1:0] $end
$var reg 8 / last_byte [7:0] $end
$var reg 1 0 prev_req $end
$upscope $end
$upscope $end
$upscope $end
$enddefinitions $end
#0
$dumpvars
x0
bx /
bx .
bx -
bx ,
bx +
bx *
bx )
bx (
x'
bx &
bx %
x$
1#
0"
0!
$end
#5000
b0 )
b1 +
b10100000 &
b10100000 (
b10100000 -
1$
b0 *
b0 ,
b0 %
b0 /
b0 .
0'
00
1"
#10000
0"
#15000
b1 +
b10100000 &
b10100000 (
b10100000 -
1$
1"
#20000
0"
0#
#25000
b10 +
0$
b1 ,
b1 .
1'
b10100000 %
b10100000 /
10
1"
#30000
0"
#35000
b10 .
00
b10 ,
1"
#40000
0"
#45000
b1 +
1$
b10100001 &
b10100001 (
b10100001 -
b1 )
b0 .
0'
1"
#50000
0"
#55000
b10 +
0$
b1 .
1'
b10100001 %
b10100001 /
10
b1 *
b1 ,
1"
#60000
0"
#65000
b10 ,
b10 .
00
1"
#70000
0"
#75000
b1 +
1$
b10100010 &
b10100010 (
b10100010 -
b10 )
b0 .
0'
1"
#80000
0"
#85000
b10 +
0$
b10 *
b1 ,
b1 .
1'
b10100010 %
b10100010 /
10
1"
#90000
0"
#95000
b10 .
00
b10 ,
1"
#100000
0"
#105000
b1 +
1$
b10100011 &
b10100011 (
b10100011 -
b11 )
b0 .
0'
1"
#110000
0"
#115000
b10 +
0$
b1 .
1'
b10100011 %
b10100011 /
10
b11 *
b1 ,
1"
#120000
0"
#125000
b10 ,
b10 .
00
1"
#130000
0"
#135000
b11 +
1!
b0 .
0'
1"
#140000
0"
#145000
b0 +
0!
b11 ,
1"
